buildincr.py
buildincr-0.1.2.dist-info/licenses/LICENSE
buildincr-0.1.2.dist-info/METADATA
buildincr-0.1.2.dist-info/WHEEL
buildincr-0.1.2.dist-info/entry_points.txt
buildincr-0.1.2.dist-info/top_level.txt
buildincr-0.1.2.dist-info/RECORD
