Metadata-Version: 2.4
Name: buildincr
Version: 0.1.2
Summary: Increment the value in the build-serial-file by one.
Author: rRR0VrFP
Maintainer: rRR0VrFP
License: MIT
Keywords: buildincr
Classifier: Development Status :: 5 - Production/Stable
Classifier: Intended Audience :: Developers
Classifier: Topic :: Software Development :: Libraries :: Python Modules
Classifier: License :: OSI Approved :: MIT License
Classifier: Programming Language :: Python :: 3
Classifier: Programming Language :: Python :: 3 :: Only
License-File: LICENSE
Requires-Dist: portalocker
Requires-Dist: click
Dynamic: author
Dynamic: classifier
Dynamic: description
Dynamic: description-content-type
Dynamic: keywords
Dynamic: license
Dynamic: license-file
Dynamic: maintainer
Dynamic: requires-dist
Dynamic: summary
